ggshu/__init__.py
ggshu/aes.py
ggshu/geoms.py
ggshu/ggdata.py
ggshu/jupyter.py
ggshu-0.2.1.dist-info/METADATA
ggshu-0.2.1.dist-info/WHEEL
ggshu-0.2.1.dist-info/top_level.txt
ggshu-0.2.1.dist-info/RECORD
