Metadata-Version: 2.4
Name: ggshu
Version: 0.2.1
Summary: Grammar of Graphics for shu.
Author-email: carrascomj <carrascomurielj@gmail.com>
Maintainer-email: carrascomj <carrascomurielj@gmail.com>
Project-URL: Homepage, https://biosustain.github.io/shu/
Project-URL: Documentation, https://biosustain.github.io/shu/plotting.html
Project-URL: Repository, https://github.com/biosustain/shu.git
Classifier: Programming Language :: Python :: 3
Requires-Python: >=3.10
Requires-Dist: pandas==2.*
Requires-Dist: numpy
Requires-Dist: IPython==8.18.1
Requires-Dist: requests>=2.32.3
Provides-Extra: dev
Requires-Dist: pytest==7.2.0; extra == "dev"
Requires-Dist: black==22.10.0; extra == "dev"
Requires-Dist: isort==5.10.1; extra == "dev"
